[
  {
    "name": "Bismuth",
    "type": "Metal & Stone",
    "items": [
      {
        "id": 210930,
        "auctions": 824,
        "price": 34.99
      },
      {
        "id": 210931,
        "auctions": 1397,
        "price": 44.64
      },
      {
        "id": 210932,
        "auctions": 924,
        "price": 250.04
      }
    ]
  },
  {
    "name": "Aqirite",
    "type": "Metal & Stone",
    "items": [
      {
        "id": 210933,
        "auctions": 709,
        "price": 21
      },
      {
        "id": 210934,
        "auctions": 1237,
        "price": 29.87
      },
      {
        "id": 210935,
        "auctions": 400,
        "price": 36.48
      }
    ]
  },
  {
    "name": "Ironclaw Ore",
    "type": "Metal & Stone",
    "items": [
      {
        "id": 210936,
        "auctions": 675,
        "price": 21
      },
      {
        "id": 210937,
        "auctions": 879,
        "price": 32.73
      },
      {
        "id": 210938,
        "auctions": 1547,
        "price": 42.03
      }
    ]
  },
  {
    "name": "Mycobloom",
    "type": "Herb",
    "items": [
      {
        "id": 210796,
        "auctions": 641,
        "price": 23
      },
      {
        "id": 210797,
        "auctions": 945,
        "price": 27.27
      },
      {
        "id": 210798,
        "auctions": 693,
        "price": 31.88
      }
    ]
  },
  {
    "name": "Luredrop",
    "type": "Herb",
    "items": [
      {
        "id": 210799,
        "auctions": 621,
        "price": 69.4
      },
      {
        "id": 210800,
        "auctions": 1428,
        "price": 77.9
      },
      {
        "id": 210801,
        "auctions": 1391,
        "price": 403.99
      }
    ]
  },
  {
    "name": "Orbinid",
    "type": "Herb",
    "items": [
      {
        "id": 210802,
        "auctions": 1471,
        "price": 24.55
      },
      {
        "id": 210803,
        "auctions": 775,
        "price": 64.99
      },
      {
        "id": 210804,
        "auctions": 776,
        "price": 346.96
      }
    ]
  },
  {
    "name": "Blessing Blossom",
    "type": "Herb",
    "items": [
      {
        "id": 210805,
        "auctions": 453,
        "price": 11.01
      },
      {
        "id": 210806,
        "auctions": 918,
        "price": 39.85
      },
      {
        "id": 210807,
        "auctions": 1322,
        "price": 211.98
      }
    ]
  },
  {
    "name": "Arathor's Spear",
    "type": "Herb",
    "items": [
      {
        "id": 210808,
        "auctions": 1764,
        "price": 56
      },
      {
        "id": 210809,
        "auctions": 1769,
        "price": 108.87
      },
      {
        "id": 210810,
        "auctions": 1444,
        "price": 630.6
      }
    ]
  }
]