[
  {
    "name": "Bismuth",
    "type": "Metal & Stone",
    "items": [
      {
        "id": 210930,
        "auctions": 878,
        "price": 36.53
      },
      {
        "id": 210931,
        "auctions": 479,
        "price": 52.98
      },
      {
        "id": 210932,
        "auctions": 488,
        "price": 280
      }
    ]
  },
  {
    "name": "Aqirite",
    "type": "Metal & Stone",
    "items": [
      {
        "id": 210933,
        "auctions": 648,
        "price": 14.97
      },
      {
        "id": 210934,
        "auctions": 592,
        "price": 25.99
      },
      {
        "id": 210935,
        "auctions": 1005,
        "price": 38.54
      }
    ]
  },
  {
    "name": "Ironclaw Ore",
    "type": "Metal & Stone",
    "items": [
      {
        "id": 210936,
        "auctions": 631,
        "price": 17.82
      },
      {
        "id": 210937,
        "auctions": 428,
        "price": 24.7
      },
      {
        "id": 210938,
        "auctions": 585,
        "price": 39.47
      }
    ]
  },
  {
    "name": "Mycobloom",
    "type": "Herb",
    "items": [
      {
        "id": 210796,
        "auctions": 1043,
        "price": 16.98
      },
      {
        "id": 210797,
        "auctions": 990,
        "price": 22.7
      },
      {
        "id": 210798,
        "auctions": 1048,
        "price": 33
      }
    ]
  },
  {
    "name": "Luredrop",
    "type": "Herb",
    "items": [
      {
        "id": 210799,
        "auctions": 2261,
        "price": 45.32
      },
      {
        "id": 210800,
        "auctions": 1792,
        "price": 75.27
      },
      {
        "id": 210801,
        "auctions": 800,
        "price": 418.9
      }
    ]
  },
  {
    "name": "Orbinid",
    "type": "Herb",
    "items": [
      {
        "id": 210802,
        "auctions": 1190,
        "price": 18.19
      },
      {
        "id": 210803,
        "auctions": 1157,
        "price": 58
      },
      {
        "id": 210804,
        "auctions": 433,
        "price": 318.91
      }
    ]
  },
  {
    "name": "Blessing Blossom",
    "type": "Herb",
    "items": [
      {
        "id": 210805,
        "auctions": 684,
        "price": 12.01
      },
      {
        "id": 210806,
        "auctions": 722,
        "price": 23.99
      },
      {
        "id": 210807,
        "auctions": 1183,
        "price": 96.01
      }
    ]
  },
  {
    "name": "Arathor's Spear",
    "type": "Herb",
    "items": [
      {
        "id": 210808,
        "auctions": 1804,
        "price": 31.99
      },
      {
        "id": 210809,
        "auctions": 1035,
        "price": 88.56
      },
      {
        "id": 210810,
        "auctions": 536,
        "price": 469
      }
    ]
  }
]