[
  {
    "name": "Bismuth",
    "type": "Metal & Stone",
    "items": [
      {
        "id": 210930,
        "auctions": 3348,
        "price": 24.92
      },
      {
        "id": 210931,
        "auctions": 1249,
        "price": 35.94
      },
      {
        "id": 210932,
        "auctions": 501,
        "price": 199.89
      }
    ]
  },
  {
    "name": "Aqirite",
    "type": "Metal & Stone",
    "items": [
      {
        "id": 210933,
        "auctions": 778,
        "price": 14.67
      },
      {
        "id": 210934,
        "auctions": 1778,
        "price": 23.51
      },
      {
        "id": 210935,
        "auctions": 556,
        "price": 38
      }
    ]
  },
  {
    "name": "Ironclaw Ore",
    "type": "Metal & Stone",
    "items": [
      {
        "id": 210936,
        "auctions": 895,
        "price": 13.72
      },
      {
        "id": 210937,
        "auctions": 771,
        "price": 16.49
      },
      {
        "id": 210938,
        "auctions": 1374,
        "price": 37
      }
    ]
  },
  {
    "name": "Mycobloom",
    "type": "Herb",
    "items": [
      {
        "id": 210796,
        "auctions": 3550,
        "price": 16.48
      },
      {
        "id": 210797,
        "auctions": 2047,
        "price": 18.1
      },
      {
        "id": 210798,
        "auctions": 1995,
        "price": 31
      }
    ]
  },
  {
    "name": "Luredrop",
    "type": "Herb",
    "items": [
      {
        "id": 210799,
        "auctions": 840,
        "price": 60.37
      },
      {
        "id": 210800,
        "auctions": 1925,
        "price": 82.8
      },
      {
        "id": 210801,
        "auctions": 1420,
        "price": 442.45
      }
    ]
  },
  {
    "name": "Orbinid",
    "type": "Herb",
    "items": [
      {
        "id": 210802,
        "auctions": 559,
        "price": 15.66
      },
      {
        "id": 210803,
        "auctions": 1217,
        "price": 42.65
      },
      {
        "id": 210804,
        "auctions": 511,
        "price": 236.9
      }
    ]
  },
  {
    "name": "Blessing Blossom",
    "type": "Herb",
    "items": [
      {
        "id": 210805,
        "auctions": 1287,
        "price": 11.81
      },
      {
        "id": 210806,
        "auctions": 1189,
        "price": 22.99
      },
      {
        "id": 210807,
        "auctions": 1305,
        "price": 103.86
      }
    ]
  },
  {
    "name": "Arathor's Spear",
    "type": "Herb",
    "items": [
      {
        "id": 210808,
        "auctions": 1826,
        "price": 27.99
      },
      {
        "id": 210809,
        "auctions": 867,
        "price": 68.56
      },
      {
        "id": 210810,
        "auctions": 99,
        "price": 494.9
      }
    ]
  }
]